setup.py
pyLCD.egg-info/PKG-INFO
pyLCD.egg-info/SOURCES.txt
pyLCD.egg-info/dependency_links.txt
pyLCD.egg-info/requires.txt
pyLCD.egg-info/top_level.txt
pylcd/PyQRNative.py
pylcd/__init__.py
pylcd/backends.py
pylcd/hd44780.py
pylcd/inputs.py
pylcd/ks0108.py
pylcd/metadata.py
pylcd/utils.py