Metadata-Version: 1.0
Name: pyLCD
Version: 1.1.3
Summary: A library for controlling LCDs on various hardware backends
Home-page: https://github.com/Mezgrman/pyLCD
Author: Julian Metzler
Author-email: pylcd@mezgr.de
License: AGPLv3
Keywords: library lcd display hd44780 ks0108 interface
Platform: UNKNOWN
